uk_charities_mcp/__init__.py
uk_charities_mcp/client.py
uk_charities_mcp/models.py
uk_charities_mcp/server.py
uk_charities_mcp-0.1.0.dist-info/METADATA
uk_charities_mcp-0.1.0.dist-info/WHEEL
uk_charities_mcp-0.1.0.dist-info/entry_points.txt
uk_charities_mcp-0.1.0.dist-info/licenses/LICENSE
uk_charities_mcp-0.1.0.dist-info/RECORD
