Metadata-Version: 2.4
Name: uk-charities-mcp
Version: 0.1.0
Summary: MCP server for querying UK Charity Commission data via CharityBase
License-File: LICENSE
Requires-Python: >=3.14
Requires-Dist: httpx>=0.28.1
Requires-Dist: mcp[cli]>=1.25.0
Requires-Dist: pydantic>=2.12.5
